{
  "placeholderImages": [
    {
      "id": "hero-background",
      "description": "Stressed passenger at an airport, looking at the flight information board.",
      "imageUrl": "https://images.unsplash.com/photo-1582016309400-7003ea03ef95?crop=entropy&cs=tinysrgb&fit=max&fm=jpg&ixid=M3w3NDE5ODJ8MHwxfHNlYXJjaHwzfHxhaXJwb3J0JTIwcGFzc2VuZ2VyfGVufDB8fHx8MTc2ODQxNDQ1MHww&ixlib=rb-4.1.0&q=80&w=1080",
      "imageHint": "airport passenger"
    },
    {
      "id": "specialist-photo",
      "description": "Professional headshot of Dr. Danillo Campos Rocha Peixoto.",
      "imageUrl": "https://raw.githubusercontent.com/LPMarketing/Danillo/da5fbce5e2386e01f3343f7b5b3318335fde917c/thub.jpg",
      "imageHint": "lawyer portrait"
    }
  ]
}